<?xml version="1.0" encoding="utf-8"?>
	<!--设备信息-->
<equipment>				
	<child>
	    <!-- 冷水泵1 -->
		<area title="盥洗泵1#" wd="20" hg="20" marLeft="620" marTop="425" prop="lsb"
			initFlag="hidden" eqTypeId="5004" positionX="100" postionY="50" eventType="click"></area>
			
		<!-- 冷水泵2 -->
		<area title="盥洗泵2#" wd="20" hg="20" marLeft="515" marTop="390" prop="lsb"
			initFlag="hidden" eqTypeId="5004" positionX="100" postionY="50" eventType="click"></area>
		
		<!-- 冷水泵3 -->
		<area title="淋浴泵1#" wd="20" hg="20" marLeft="345" marTop="330" prop="lsb"
			initFlag="hidden" eqTypeId="5004" positionX="100" postionY="50" eventType="click"></area>
			
		<!-- 冷水泵4 -->
		<area title="淋浴泵2#" wd="20" hg="20" marLeft="270" marTop="300" prop="lsb"
			initFlag="hidden" eqTypeId="5004" positionX="100" postionY="50" eventType="click"></area>
			
		<!-- 换热器1 -->	
		<area title="换热器1#" wd="20" hg="20" marLeft="450" marTop="260" prop="hrq"
			initFlag="hidden" eqTypeId="5005" positionX="100" postionY="50" eventType="click"></area>
		
		<!-- 换热器2 -->	
		<area title="换热器2#" wd="20" hg="20" marLeft="560" marTop="290" prop="hrq"
			initFlag="hidden" eqTypeId="5005" positionX="100" postionY="50" eventType="click"></area>
	</child>		
</equipment>